modular_rl/__init__.py
modular_rl/networks.py
modular_rl/settings.py
modular_rl/tester.py
modular_rl/agents/__init__.py
modular_rl/agents/_agent.py
modular_rl/agents/_custom.py
modular_rl/agents/agent_ppo.py
modular_rl/agents/mcis.py
modular_rl/agents/mcts.py
modular_rl/agents/mim.py
modular_rl/agents/ppo.py
modular_rl/agents/_common/__init__.py
modular_rl/agents/_common/_agents.py
modular_rl/agents/pytorch/__init__.py
modular_rl/agents/pytorch/_agent.py
modular_rl/agents/pytorch/mcis.py
modular_rl/agents/pytorch/mcts.py
modular_rl/agents/pytorch/ppo.py
modular_rl/agents/tensorflow/__init__.py
modular_rl/agents/tensorflow/_agent.py
modular_rl/agents/tensorflow/mcis.py
modular_rl/agents/tensorflow/mcts.py
modular_rl/agents/tensorflow/ppo.py
modular_rl/envs/__init__.py
modular_rl/envs/_custom.py
modular_rl/envs/mim/__init__.py
modular_rl/envs/mim/card_evaluator.py
modular_rl/envs/mim/mim.py
modular_rl/networks/__init__.py
modular_rl/networks/actor_critic.py
modular_rl/networks/policy.py
modular_rl/networks/value.py
modular_rl/networks/pytorch/__init__.py
modular_rl/networks/pytorch/actor_critic.py
modular_rl/networks/pytorch/policy.py
modular_rl/networks/pytorch/value.py
modular_rl/networks/tensorflow/__init__.py
modular_rl/networks/tensorflow/actor_critic.py
modular_rl/networks/tensorflow/policy.py
modular_rl/networks/tensorflow/value.py
modular_rl/params/__init__.py
modular_rl/params/mcis.py
modular_rl/params/mcts.py
modular_rl/params/mim.py
modular_rl/params/ppo.py
modular_rl/tester/__init__.py
modular_rl/tester/mcis.py
modular_rl/tester/mcts.py
modular_rl/tester/mim.py
modular_rl/tester/ppo.py
modular_rl/util/__init__.py
modular_rl/util/node.py
modular_rl-0.4.3.dist-info/LICENSE
modular_rl-0.4.3.dist-info/METADATA
modular_rl-0.4.3.dist-info/WHEEL
modular_rl-0.4.3.dist-info/top_level.txt
modular_rl-0.4.3.dist-info/RECORD
