Metadata-Version: 2.1
Name: modular-rl
Version: 0.4.3
Summary: ModularRL is a Python library for creating and training reinforcement learning agents using various algorithms. The library is designed to be easily customizable and modular, allowing users to quickly set up and train agents for various environments without being limited to a specific algorithm.
Home-page: https://github.com/horrible-gh/ModularRL
Author: sjm
Author-email: horrible <shinjpn1@gmail.com>
Project-URL: Homepage, https://github.com/horrible-gh/ModularRL
Project-URL: Bug Tracker, https://github.com/horrible-gh/ModularRL/issues
Keywords: ModularRL,Modular-RL,Modular_RL,Modular RL,modularrl,modular_rl,modular-rl,modular rl,mrl,modular,learn,learning,pytorch learn,pytorch learning,tensorflow learn,tensorflow learning,ai
Classifier: Programming Language :: Python :: 3
Classifier: License :: OSI Approved :: MIT License
Classifier: Operating System :: OS Independent
Classifier: Programming Language :: Python :: 3
Classifier: Programming Language :: Python :: 3.6
Classifier: Programming Language :: Python :: 3.7
Classifier: Programming Language :: Python :: 3.8
Classifier: Programming Language :: Python :: 3.9
Classifier: Programming Language :: Python :: 3.10
Classifier: Programming Language :: Python :: 3.11
Requires-Python: >=3.6
License-File: LICENSE
Requires-Dist: gym
Requires-Dist: numpy
Requires-Dist: torch
Requires-Dist: LogAssist
Requires-Dist: tensorflow
Requires-Dist: tensorflow-probability
